classicmenu_indicator/__init__.py
classicmenu_indicator/_meta.py
classicmenu_indicator/about.py
classicmenu_indicator/cmindicator.py
classicmenu_indicator/dialogs.py
classicmenu_indicator/preferencesdlg.py
classicmenu_indicator/settings.py
classicmenu_indicator/tvtools.py
classicmenu_indicator-0.11.data/data/share/applications/classicmenu-indicator.desktop
classicmenu_indicator-0.11.data/data/share/classicmenu-indicator/all_apps.menu
classicmenu_indicator-0.11.data/data/share/classicmenu-indicator/applications.menu
classicmenu_indicator-0.11.data/data/share/classicmenu-indicator/classicmenuindicatorsystem.menu
classicmenu_indicator-0.11.data/data/share/classicmenu-indicator/ui/preferences.ui
classicmenu_indicator-0.11.data/data/share/locale/am/LC_MESSAGES/classicmenu-indicator.mo
classicmenu_indicator-0.11.data/data/share/locale/ar/LC_MESSAGES/classicmenu-indicator.mo
classicmenu_indicator-0.11.data/data/share/locale/bg/LC_MESSAGES/classicmenu-indicator.mo
classicmenu_indicator-0.11.data/data/share/locale/ca/LC_MESSAGES/classicmenu-indicator.mo
classicmenu_indicator-0.11.data/data/share/locale/ckb/LC_MESSAGES/classicmenu-indicator.mo
classicmenu_indicator-0.11.data/data/share/locale/de/LC_MESSAGES/classicmenu-indicator.mo
classicmenu_indicator-0.11.data/data/share/locale/el/LC_MESSAGES/classicmenu-indicator.mo
classicmenu_indicator-0.11.data/data/share/locale/es/LC_MESSAGES/classicmenu-indicator.mo
classicmenu_indicator-0.11.data/data/share/locale/et/LC_MESSAGES/classicmenu-indicator.mo
classicmenu_indicator-0.11.data/data/share/locale/eu/LC_MESSAGES/classicmenu-indicator.mo
classicmenu_indicator-0.11.data/data/share/locale/fi/LC_MESSAGES/classicmenu-indicator.mo
classicmenu_indicator-0.11.data/data/share/locale/fr/LC_MESSAGES/classicmenu-indicator.mo
classicmenu_indicator-0.11.data/data/share/locale/gl/LC_MESSAGES/classicmenu-indicator.mo
classicmenu_indicator-0.11.data/data/share/locale/hr/LC_MESSAGES/classicmenu-indicator.mo
classicmenu_indicator-0.11.dist-info/DESCRIPTION.rst
classicmenu_indicator-0.11.dist-info/METADATA
classicmenu_indicator-0.11.dist-info/RECORD
classicmenu_indicator-0.11.dist-info/WHEEL
classicmenu_indicator-0.11.dist-info/entry_points.txt
classicmenu_indicator-0.11.dist-info/metadata.json
classicmenu_indicator-0.11.dist-info/top_level.txt
