Metadata-Version: 2.0
Name: classicmenu-indicator
Version: 0.11
Summary: An Unity indicator applet that provides the classic GNOME application menu
Home-page: http://www.florian-diesch.de/software/classicmenu-indicator/
Author: Florian Diesch
Author-email: devel@florian-diesch.de
License: GPLv3
Download-URL: http://www.florian-diesch.de/software/classicmenu-indicator/
Keywords: Ubuntu,Unity,Indicator,Applet,Gnome,Classic Menu
Platform: UNKNOWN
Classifier: Development Status :: 4 - Beta
Classifier: Environment :: X11 Applications :: Gnome
Classifier: Intended Audience :: End Users/Desktop
Classifier: License :: OSI Approved :: GNU General Public License (GPL)
Classifier: Natural Language :: English
Classifier: Natural Language :: German
Classifier: Operating System :: POSIX :: Linux
Classifier: Programming Language :: Python :: 3
Classifier: Topic :: Desktop Environment :: Gnome
Classifier: Topic :: Utilities
